routes1846/__init__.py
routes1846/board.py
routes1846/boardstate.py
routes1846/boardtile.py
routes1846/cell.py
routes1846/find_best_routes.py
routes1846/placedtile.py
routes1846/private_companies.py
routes1846/railroads.py
routes1846/route.py
routes1846/tiles.py
routes1846/tokens.py
routes1846/data/base-board.json
routes1846/data/tiles.json
routes_1846-0.22.dist-info/LICENSE
routes_1846-0.22.dist-info/METADATA
routes_1846-0.22.dist-info/WHEEL
routes_1846-0.22.dist-info/top_level.txt
routes_1846-0.22.dist-info/RECORD
