Metadata-Version: 2.1
Name: routes-1846
Version: 0.22
Summary: Library for caluclating routes in 1846: The Race For The Midwest.
Home-page: https://github.com/Auzzy/1846-routes
Author: Austin Noto-Moniz
Author-email: metalnut4@netscape.net
License: UNKNOWN
Platform: UNKNOWN
Classifier: Development Status :: 4 - Beta
Classifier: Operating System :: OS Independent
Classifier: Programming Language :: Python :: 3
Classifier: License :: OSI Approved :: MIT License
